aiplatgo/__init__.py
aiplatgo/cli.py
aiplatgo/command.py
aiplatgo/gcs.py
aiplatgo/parser.py
aiplatgo/utils.py
aiplatgo/config/flags.yaml
aiplatgo-0.0.0.18.dist-info/METADATA
aiplatgo-0.0.0.18.dist-info/WHEEL
aiplatgo-0.0.0.18.dist-info/entry_points.txt
aiplatgo-0.0.0.18.dist-info/top_level.txt
aiplatgo-0.0.0.18.dist-info/RECORD
