Metadata-Version: 2.1
Name: aiplatgo
Version: 0.0.0.18
Summary: CLI wrapper for `gcloud ai-platform`
Home-page: https://github.com/brookisme/aiplatgo
Author: Brookie Guzder-Williams
Author-email: brook.williams@gmail.com
License: UNKNOWN
Download-URL: https://github.com/brookisme/aiplatgo/tarball/0.1
Keywords: python,tensorflow,gcloud,ai-platform,CLI
Platform: UNKNOWN
Requires-Dist: click
Requires-Dist: pandas
Requires-Dist: pyyaml
Requires-Dist: mproc
Requires-Dist: gcs-helpers (>=0.0.0.22)
